cirrus_ngs-1.0.0a1.dist-info/METADATA
cirrus_ngs-1.0.0a1.dist-info/RECORD
cirrus_ngs-1.0.0a1.dist-info/WHEEL
cirrus_ngs-1.0.0a1.dist-info/entry_points.txt
cirrus_ngs-1.0.0a1.dist-info/top_level.txt
cirrusngs/__init__.py
cirrusngs/cirrus.yaml
cirrusngs/cirrusngs.py
cirrusngs/cli.py
cirrusngs/design_files/ChIPSeq_design_example.txt
cirrusngs/design_files/DNASeq_design_example.txt
cirrusngs/design_files/RNASeq_design_example.txt
cirrusngs/design_files/WES_design_example.txt
cirrusngs/design_files/WGS_design_example.txt
cirrusngs/design_files/miRNASeq_design_example.txt
cirrusngs/managers/AddonsManager.py
cirrusngs/managers/CFNClusterManager.py
cirrusngs/managers/ConnectionManager.py
cirrusngs/managers/PipelineManager.py
cirrusngs/managers/__init__.py
cirrusngs/notebooks/BasicCFNClusterSetup.ipynb
cirrusngs/notebooks/ChIPSeqTemplate.ipynb
cirrusngs/notebooks/DNASeqTemplate.ipynb
cirrusngs/notebooks/RNASeqTemplate.ipynb
cirrusngs/notebooks/WESTemplate.ipynb
cirrusngs/notebooks/WGSTemplate.ipynb
cirrusngs/notebooks/miRNASeqTemplate.ipynb
cirrusngs/notebooks/.ipynb_checkpoints/BasicCFNClusterSetup-checkpoint.ipynb
cirrusngs/notebooks/.ipynb_checkpoints/ChIPSeqPipeline-checkpoint.ipynb
cirrusngs/notebooks/.ipynb_checkpoints/ChIPSeqTemplate-checkpoint.ipynb
cirrusngs/notebooks/.ipynb_checkpoints/CheckScripts-checkpoint.ipynb
cirrusngs/notebooks/.ipynb_checkpoints/ChiPSeq Pipeline-checkpoint.ipynb
cirrusngs/notebooks/.ipynb_checkpoints/ChiPSeqPipeline-checkpoint.ipynb
cirrusngs/notebooks/.ipynb_checkpoints/DNASeqTemplate-checkpoint.ipynb
cirrusngs/notebooks/.ipynb_checkpoints/RNASeq Pipeline-checkpoint.ipynb
cirrusngs/notebooks/.ipynb_checkpoints/RNASeqTemplate-checkpoint.ipynb
cirrusngs/notebooks/.ipynb_checkpoints/RNA_Pipeline-checkpoint.ipynb
cirrusngs/notebooks/.ipynb_checkpoints/miRNASeqTemplate-checkpoint.ipynb
cirrusngs/notebooks/deprecated/BasicCFNClusterSetup.ipynb
cirrusngs/notebooks/deprecated/ChIPSeqPipeline.ipynb
cirrusngs/notebooks/deprecated/CheckScripts.ipynb
cirrusngs/notebooks/deprecated/CirrusAddons.ipynb
cirrusngs/notebooks/deprecated/RNASeq Pipeline.ipynb
cirrusngs/notebooks/deprecated/RNASeqTemplate.ipynb
