Metadata-Version: 2.1
Name: cirrus-ngs
Version: 1.0.0a1
Summary: Cloud-optimized primary analysis pipelines for RNA-seq, miRNA-seq, ChIP-seq, and variant calling in whole-genome/whole-exome DNA-seq
Home-page: https://github.com/ucsd-ccbb/cirrus-ngs
Author: Mustafa Guler
Author-email: mguler@ucsd.edu
Maintainer: Mustafa Guler
Maintainer-email: mguler@ucsd.edu
License: MIT
Keywords: bioinformatics,NGS,jupyter
Platform: UNKNOWN
Classifier: License :: OSI Approved :: MIT License
Classifier: Intended Audience :: Science/Research
Classifier: License :: OSI Approved :: MIT License
Classifier: Operating System :: MacOS :: MacOS X
Classifier: Operating System :: POSIX :: Linux
Classifier: Programming Language :: Python :: 3.6
Classifier: Topic :: Scientific/Engineering :: Bio-Informatics
Requires-Python: >=3.5
Requires-Dist: paramiko
Requires-Dist: pyyaml
Requires-Dist: jupyter
Requires-Dist: notebook
Requires-Dist: scp
Requires-Dist: cfncluster
